Metadata-Version: 2.1
Name: odoo9-addon-website-portal-v10
Version: 9.0.1.0.0.99.dev18
Summary: Account Management Frontend for your Customers
Home-page: UNKNOWN
Author: Odoo S.A., Tecnativa, Odoo Community Association (OCA)
Author-email: support@odoo-community.org
License: LGPL-3
Platform: UNKNOWN
Classifier: Programming Language :: Python
Classifier: Framework :: Odoo
Classifier: License :: OSI Approved :: GNU Lesser General Public License v3 (LGPLv3)
Requires-Python: ~=2.7
Requires-Dist: odoo (<9.1a,>=9.0a)
